szrpc/__init__.py
szrpc/client.py
szrpc/log.py
szrpc/server.py
szrpc/result/__init__.py
szrpc/result/gresult.py
szrpc/result/qresult.py
szrpc-2024.9.0.dist-info/METADATA
szrpc-2024.9.0.dist-info/WHEEL
szrpc-2024.9.0.dist-info/top_level.txt
szrpc-2024.9.0.dist-info/RECORD
