Metadata-Version: 2.1
Name: szrpc
Version: 2024.9.0
Summary: A simple Python RPC Library using ZeroMQ & MsgPack
Home-page: https://github.com/michel4j/swift-rpc
Author: Michel Fodje
Author-email: michel4j@gmail.com
License: MIT
Keywords: rpc networking development
Classifier: Intended Audience :: Developers
Classifier: Programming Language :: Python :: 3
Classifier: License :: OSI Approved :: MIT License
Classifier: Operating System :: OS Independent
Requires-Dist: pyzmq
Requires-Dist: msgpack
Requires-Dist: setuptools-scm
Requires-Dist: importlib-metadata~=1.0; python_version < "3.8"
